<workunit extends="wtemplates/gov/treasury/BasicCashReceiptController.xml">
    <invokers>
        <invoker type="collectiontype:handler" caption="Miscellaneous" name="misc-multi-receipt" index="-1"  />
        <invoker type="cashreceipt:misc-multi-receipt" action="init" caption="Issue Receipt"/>
    </invokers>
    
    <code class="com.rameses.gov.treasury.cashreceipt.models.MiscMultiCashReceiptModel"/>
    
    <pages>
        <page template="com.rameses.gov.treasury.cashreceipt.views.MiscMultiCashReceiptPage"/>
    </pages>    
</workunit>